GCN4LP-0.1.dist-info/METADATA
GCN4LP-0.1.dist-info/RECORD
GCN4LP-0.1.dist-info/WHEEL
GCN4LP-0.1.dist-info/top_level.txt
GCN4LP-0.1.dist-info/zip-safe
model/__init__.py
src/__init__.py
src/arga/__init__.py
src/arga/model.py
src/arga/predict.py
src/arga/train.py
src/graph_att_gae/__init__.py
src/graph_att_gae/model.py
src/graph_att_gae/predict.py
src/graph_att_gae/train.py
src/graph_att_gan/__init__.py
src/graph_att_gan/model.py
src/graph_att_gan/predict.py
src/graph_att_gan/train.py
src/graph_nheads_att_gae/__init__.py
src/graph_nheads_att_gae/model.py
src/graph_nheads_att_gae/predict.py
src/graph_nheads_att_gae/train.py
src/graph_nheads_att_gan/__init__.py
src/graph_nheads_att_gan/model.py
src/graph_nheads_att_gan/predict.py
src/graph_nheads_att_gan/train.py
src/util/__init__.py
src/util/define_optimizer.py
src/util/load_data.py
src/util/loss.py
src/util/metrics.py
src/vgae/__init__.py
src/vgae/model.py
src/vgae/predict.py
src/vgae/train.py
