Metadata-Version: 2.1
Name: GCN4LP
Version: 0.1
Summary: gcn for prediction of protein interactions
Home-page: https://github.com/jiangnanboy/gcn_for_prediction_of_protein_interactions
Author: ShiYan
Author-email: 2229029156@qq.com
License: Apache 2.0
Keywords: NLP,Link Prediction,gcn for prediction of protein interactions
Platform: Windows
Platform: Linux
Platform: Solaris
Platform: Mac OS-X
Platform: Unix
Classifier: Intended Audience :: Developers
Classifier: Operating System :: OS Independent
Classifier: Natural Language :: Chinese (Simplified)
Classifier: Natural Language :: Chinese (Traditional)
Classifier: Programming Language :: Python
Classifier: Programming Language :: Python :: 3
Classifier: Programming Language :: Python :: 3.6
Classifier: Topic :: Text Processing :: Linguistic
Classifier: Topic :: Scientific/Engineering :: Artificial Intelligence
Requires-Python: >=3.6
License-File: LICENSE
